README.md
nb_toc.py
setup.cfg
setup.py
nb_toc.egg-info/PKG-INFO
nb_toc.egg-info/SOURCES.txt
nb_toc.egg-info/dependency_links.txt
nb_toc.egg-info/requires.txt
nb_toc.egg-info/top_level.txt