Metadata-Version: 1.1
Name: nb-toc
Version: 0.1.1
Summary: Creates a table of contents for Jupyter Notebooks
Home-page: https://github.com/tompiona/nb_toc
Author: Ronald Walker
Author-email: ronald.walker@berkeley.edu
License: UNKNOWN
Download-URL: https://github.com/tompiona/nb_toc/archive/0.1.0.tar.gz
Keywords: juypter notebook table of contents internal links hyperlinks
Platform: UNKNOWN
